plcstream2py/__init__.py
plcstream2py/plc.py
plcstream2py/raw_plc.py
plcstream2py-0.0.2.dist-info/LICENSE
plcstream2py-0.0.2.dist-info/METADATA
plcstream2py-0.0.2.dist-info/WHEEL
plcstream2py-0.0.2.dist-info/top_level.txt
plcstream2py-0.0.2.dist-info/RECORD
